anchoring/__init__.py
anchoring/spa.py
anchoring/spa_pipeline.py
anchoring-0.1.0.dist-info/licenses/LICENSE
anchoring-0.1.0.dist-info/METADATA
anchoring-0.1.0.dist-info/WHEEL
anchoring-0.1.0.dist-info/top_level.txt
anchoring-0.1.0.dist-info/RECORD
