Metadata-Version: 2.4
Name: anchoring
Version: 0.1.0
Summary: Selective Prompt Anchoring (SPA) for LLMs
Home-page: https://github.com/magic-YuanTian/Selective-Prompt-Anchoring
Author: Yuan Tian
Author-email: bestaskwisher@gmail.com
Classifier: Programming Language :: Python :: 3
Classifier: License :: OSI Approved :: MIT License
Classifier: Operating System :: OS Independent
Requires-Python: >=3.8
License-File: LICENSE
Requires-Dist: torch>=1.10.0
Requires-Dist: transformers>=4.30.0
Dynamic: author
Dynamic: author-email
Dynamic: classifier
Dynamic: description
Dynamic: description-content-type
Dynamic: home-page
Dynamic: license-file
Dynamic: requires-dist
Dynamic: requires-python
Dynamic: summary
